Workbook

Sheet INVOICE
B2: INVOICE
B3: BULL MACHINES PVT LTD Plant 1 | E3: Type : | F3: Tax Invoice
B4: 5, 1 A, Trichy Rd, | E4: Tax Inv No : | F4: 103/2026-27
B5: Chinthamanipudur, | E5: INV Date : | F5: 46240
B6: Coimbatore -641 103, | E6: GST No : | F6: 33AAGCJ6200N1ZL
B7: Tamilnadu, India. | E7: PAN No : | F7: AAGCJ6200N
B8: GST NO : 33AAACB8772D1ZV | E8: Tax Payable on Reverse Charges | F8: NO
B9: SI.NO | C9: Description | E9: Category of Service | F9: SAC Code
C10: Towards Labour Charges for the following works carried out at your premises on your behalf in period of 01-07-2026 to 31-07-2026 | E10: Other Employment and Labour Supply Services | F10: 998519
B11: 1 | C11: Total earnings | F11: ='PLANT 1'!D22 -> 128725
B12: 2 | C12: OT Earnings | F12: ='PLANT 1'!D23 -> 73160
B13: 2 | C13: EPF 13% | F13: ='PLANT 1'!D24 -> 8729.5
B14: 3 | C14: ESI 3.25% | F14: ='PLANT 1'!D25 -> 3091.5625
B15: 4 | C15: Service charge 8% | F15: ='PLANT 1'!D26 -> 15990
B17: 5 | C17: GST | E17: Taxable Amount | F17: =SUM(F11:F15) -> 229696.06
C18: a) SGST 09% | D18: 0.09 | E18: =F17 -> 229696.06 | F18: =E18*9% -> 20672.646
C19: b) CGST 09% | D19: 0.09 | E19: =F17 -> 229696.06 | F19: =E19*9% -> 20672.646
C21: Grand Total | F21: =SUM(F17:F19) -> 271041.35
C22: (Annexure Attached)
C23: RUPEES: TWO LAKH SEVENTY ONE THOUSAND AND FORTY ONE ONLY

Sheet PLANT 1
A1: Sl No | B1: Emp ID | C1: Employee Name | D1: Month/ Year | E1: Pay Days | F1: Present Days | G1: Sal Cal Days | H1: BASIC | I1: HRA | J1: TA | K1: TURNPERF | L1: HODASSPERF | M1: TASKPERF | N1: PER DAY | O1: OT AMOUNT | P1: ATTD GIFT | Q1: REWARD | R1: ARREARS | S1: OT HOUR | T1: OT1 Rate | U1: CANTEEN | V1: UNIFORM | W1: SHOE | X1: OTHER DED | Y1: LVE WAIVER | Z1: BONUS Per | AA1: PF | AB1: ESI | AC1: Total Earning | AD1: Total Deduction | AE1: Net Amount | AF1: Derived Total | AG1: ESI 3.25% | AH1: PF 13% | AI1: SERVICE CHARGES | AJ1: Remark | AK1: Attendance | AL1: Branch | AM1: CADRE | AN1: Department | AO1: Designation | AP1: Grade | AQ1: Date of Joining
A2: 1 | B2: 57741 | C2: ANSE GEORGE | D2: 46204 | E2: 24 | F2: 24 | G2: 27 | H2: 18816 | I2: 3360 | J2: 1344 | K2: 5040 | L2: 2016 | M2: 3024 | N2: 1400 | O2: 11380 | P2: 0 | Q2: 0 | R2: 0 | S2: 65 | T2: 175 | U2: 832.5 | V2: 0 | W2: 0 | X2: 0 | Y2: 1 | Z2: 8.33 | AA2: 1800 | AB2: 0 | AC2: 33600 | AD2: 2632.5 | AE2: 30970 | AF2: 1400 | AH2: 1950 | AI2: =ROUND(((E2*AF2)+O2)*8%,0) -> 3598 | AK2: Attendance Joy | AL2: PLANT-I & H-DIV | AM2: LABOUR | AN2: WELDSHOP | AO2: TECHNICIAN TRAINEE | AP2: Back-Office | AQ2: 07/07/2025
A3: =A2+1 -> 2 | B3: 58790 | C3: NISHIKANT MAHTO | D3: 46204 | E3: 27 | F3: 27 | G3: 27 | H3: 10206 | I3: 1822.5 | J3: 729 | K3: 2733.75 | L3: 1093.5 | M3: 1640.25 | N3: 675 | O3: 14090 | P3: 500 | Q3: 0 | R3: 0 | S3: 167 | T3: 84.38 | U3: 843 | V3: 0 | W3: 0 | X3: 0 | Y3: 1 | Z3: 8.33 | AA3: 1225 | AB3: 137 | AC3: 18725 | AD3: 2205 | AE3: 16520 | AF3: 675 | AG3: =AC3*3.25% -> 608.5625 | AH3: =H3*13% -> 1326.78 | AI3: =ROUND(((E3*AF3)+O3)*8%,0) -> 2585 | AK3: Attendance Joy | AL3: PLANT-I & H-DIV | AM3: LABOUR | AN3: RESEARCH&DEVELOPMENT-NPD | AO3: TECHNICIAN TRAINEE | AP3: Back-Office | AQ3: 11/11/2025
A4: =A3+1 -> 3 | B4: 5000252 | C4: SANJAY REANG | D4: 46204 | E4: 27 | F4: 27 | G4: 27 | H4: 10584 | I4: 1890 | J4: 756 | K4: 2835 | L4: 1134 | M4: 1701 | N4: 700 | O4: 11990 | P4: 500 | Q4: 0 | R4: 0 | S4: 137 | T4: 87.5 | U4: 0 | V4: 0 | W4: 0 | X4: 0 | Y4: 1 | Z4: 8.33 | AA4: 1270 | AB4: 142 | AC4: 19400 | AD4: 1412 | AE4: 17990 | AF4: 700 | AG4: =AC4*3.25% -> 630.5 | AH4: =H4*13% -> 1375.92 | AI4: =ROUND(((E4*AF4)+O4)*8%,0) -> 2471 | AK4: Attendance Joy | AL4: PLANT-I & H-DIV | AM4: LABOUR | AN4: HOUSE KEEPING | AO4: HELPER | AP4: Back-Office | AQ4: 07/05/2026
A5: =A4+1 -> 4 | B5: 5000254 | C5: NORENDRA REANG | D5: 46204 | E5: 27 | F5: 27 | G5: 27 | H5: 10584 | I5: 1890 | J5: 756 | K5: 2835 | L5: 1134 | M5: 1701 | N5: 700 | O5: 11550 | P5: 500 | Q5: 0 | R5: 0 | S5: 132 | T5: 87.5 | U5: 18 | V5: 0 | W5: 0 | X5: 0 | Y5: 1 | Z5: 8.33 | AA5: 1270 | AB5: 142 | AC5: 19400 | AD5: 1430 | AE5: 17970 | AF5: 700 | AG5: =AC5*3.25% -> 630.5 | AH5: =H5*13% -> 1375.92 | AI5: =ROUND(((E5*AF5)+O5)*8%,0) -> 2436 | AK5: Attendance Joy | AL5: PLANT-I & H-DIV | AM5: LABOUR | AN5: HOUSE KEEPING | AO5: TECHNICIAN TRAINEE | AP5: Back-Office | AQ5: 07/05/2026
A6: =A5+1 -> 5 | B6: 5001053 | C6: KARTIK KUMAR REANG | D6: 46204 | E6: 27 | F6: 27 | G6: 27 | H6: 10584 | I6: 1890 | J6: 756 | K6: 2835 | L6: 1134 | M6: 1701 | N6: 700 | O6: 12250 | P6: 500 | Q6: 0 | R6: 0 | S6: 140 | T6: 87.5 | U6: 0 | V6: 0 | W6: 0 | X6: 0 | Y6: 1 | Z6: 8.33 | AA6: 1270 | AB6: 142 | AC6: 19400 | AD6: 1412 | AE6: 17990 | AF6: 700 | AG6: =AC6*3.25% -> 630.5 | AH6: =H6*13% -> 1375.92 | AI6: =ROUND(((E6*AF6)+O6)*8%,0) -> 2492 | AK6: Attendance Joy | AL6: PLANT-I & H-DIV | AM6: LABOUR | AN6: HOUSE KEEPING | AO6: Trainee Technician | AP6: Back-Office | AQ6: 18/06/2026
A7: =A6+1 -> 6 | B7: 5001054 | C7: BIBIKA REANG | D7: 46204 | E7: 26 | F7: 26 | G7: 27 | H7: 10192 | I7: 1820 | J7: 728 | K7: 2730 | L7: 1092 | M7: 1638 | N7: 700 | O7: 11900 | P7: 0 | Q7: 0 | R7: 0 | S7: 136 | T7: 87.5 | U7: 0 | V7: 0 | W7: 0 | X7: 0 | Y7: 1 | Z7: 8.33 | AA7: 1223 | AB7: 137 | AC7: 18200 | AD7: 1360 | AE7: 16840 | AF7: 700 | AG7: =AC7*3.25% -> 591.5 | AH7: =H7*13% -> 1324.96 | AI7: =ROUND(((E7*AF7)+O7)*8%,0) -> 2408 | AK7: Attendance Joy | AL7: PLANT-I & H-DIV | AM7: LABOUR | AN7: HOUSE KEEPING | AO7: Trainee Technician | AP7: Back-Office | AQ7: 18/06/2026
D8: Grand Total | E8: =SUM(E2:E7) -> 158 | F8: =SUM(F2:F7) -> 158 | G8: =SUM(G2:G7) -> 162 | H8: =SUM(H2:H7) -> 70966 | I8: =SUM(I2:I7) -> 12672.5 | J8: =SUM(J2:J7) -> 5069 | K8: =SUM(K2:K7) -> 19008.75 | L8: =SUM(L2:L7) -> 7603.5 | ... AI8: =SUM(AI2:AI7) -> 15990
C13: Career Tree PLANT-II
C14: Vendor code | D14: 700323
C15: Canteen | D15: =U8 -> 1693.5
C16: Shoe | D16: =W8 -> 0
C17: Tiffin | D17: 0
C18: Uniform | D18: =V8 -> 0
C19: Marriage | D19: 0
C20: Other Deduction | D20: =X8 -> 0
C21: Total Deduction | D21: =SUM(D15:D20) -> 1693.5
C22: Total Earnings | D22: =AC8 -> 128725
C23: OT amount | D23: =O8 -> 73160
C24: PF 13% | D24: =AH8 -> 8729.5
C25: ESI 3.25% | D25: =AG8 -> 3091.5625
C26: Service charges | D26: =AI8 -> 15990
C27: Total amount | D27: =SUM(D22:D26) -> 229696.06
C30: TAXABLE AMOUNT | D30: =D27 -> 229696.06
C31: CGST 9% | D31: =D30*9% -> 20672.646
C32: SGST 9% | D32: =D30*9% -> 20672.646
C33: GRAND TOTAL | D33: =SUM(D30:D32) -> 271041.35
